uiotedgedriverlinksdk/__init__.py
uiotedgedriverlinksdk/client.py
uiotedgedriverlinksdk/edge.py
uiotedgedriverlinksdk/exception.py
uiotedgedriverlinksdk/nats.py
uiotedge_driver_link_sdk-0.0.48.dist-info/METADATA
uiotedge_driver_link_sdk-0.0.48.dist-info/WHEEL
uiotedge_driver_link_sdk-0.0.48.dist-info/top_level.txt
uiotedge_driver_link_sdk-0.0.48.dist-info/RECORD
