Metadata-Version: 2.1
Name: uiotedge-driver-link-sdk
Version: 0.0.48
Summary: UIoT Edge Driver Link SDK
Home-page: https://pypi.org/project/uiotedge_driver_link_sdk/
Author: ucloud.cn
Author-email: joy.zhou@ucloud.cn
License: Apache 2 License
Platform: any
Requires-Dist: asyncio-nats-client (>=0.10.0)
Requires-Dist: cachetools (>=4.0.0)
